trading_backtester/__init__.py
trading_backtester/account.py
trading_backtester/backtester.py
trading_backtester/broker.py
trading_backtester/commission.py
trading_backtester/data.py
trading_backtester/indicator.py
trading_backtester/market.py
trading_backtester/order.py
trading_backtester/plotting.py
trading_backtester/position.py
trading_backtester/spread.py
trading_backtester/stats.py
trading_backtester/strategy.py
trading_backtester/trade.py
trading_backtester-1.0.0.dist-info/licenses/LICENSE
trading_backtester-1.0.0.dist-info/METADATA
trading_backtester-1.0.0.dist-info/WHEEL
trading_backtester-1.0.0.dist-info/top_level.txt
trading_backtester-1.0.0.dist-info/RECORD
