Metadata-Version: 2.4
Name: trading-backtester
Version: 1.0.0
Summary: A trading backtesting framework for Python
Home-page: https://github.com/madamskip1/trading-backtester
Author: Adamski Maciej
Author-email: madamskip1@gmail.com
License: MIT
Project-URL: Source, https://github.com/madamskip1/trading-backtester
Classifier: Development Status :: 5 - Production/Stable
Classifier: Intended Audience :: Financial and Insurance Industry
Classifier: License :: OSI Approved :: MIT License
Classifier: Operating System :: OS Independent
Classifier: Programming Language :: Python :: 3 :: Only
Classifier: Topic :: Office/Business :: Financial :: Investment
Requires-Python: >=3.6
License-File: LICENSE
Requires-Dist: numpy>=1.16.0
Requires-Dist: matplotlib>=3.0.0
Dynamic: author
Dynamic: author-email
Dynamic: classifier
Dynamic: description
Dynamic: description-content-type
Dynamic: home-page
Dynamic: license
Dynamic: license-file
Dynamic: project-url
Dynamic: requires-dist
Dynamic: requires-python
Dynamic: summary
